psyml/__init__.py
psyml/__main__.py
psyml/awsutils.py
psyml/models.py
psyml/settings.py
psyml-0.2.2.dist-info/LICENSE
psyml-0.2.2.dist-info/METADATA
psyml-0.2.2.dist-info/WHEEL
psyml-0.2.2.dist-info/entry_points.txt
psyml-0.2.2.dist-info/top_level.txt
psyml-0.2.2.dist-info/RECORD
