Metadata-Version: 2.1
Name: psyml
Version: 0.2.2
Summary: Secrets manager using AWS Parameter Store
Home-page: https://github.com/xiaket/psyml
Author: Kai Xia (夏恺)
Author-email: kaix@fastmail.com
License: UNKNOWN
Platform: UNKNOWN
Classifier: Development Status :: 4 - Beta
Classifier: Intended Audience :: Developers
Classifier: License :: OSI Approved :: MIT License
Classifier: Topic :: Utilities
